README.md
setup.py
connectme/__init__.py
connectme/__main__.py
connectme/cli.py
connectme.egg-info/PKG-INFO
connectme.egg-info/SOURCES.txt
connectme.egg-info/dependency_links.txt
connectme.egg-info/entry_points.txt
connectme.egg-info/not-zip-safe
connectme.egg-info/top_level.txt