Metadata-Version: 2.1
Name: connectme
Version: 0.0.1
Summary: ConnectME
Home-page: https://gfursin.github.io/connectme
Author: Grigori Fursin
Author-email: gfursin@gmail.com
License: Apache 2.0
Keywords: connectme
Platform: UNKNOWN
Classifier: Development Status :: 1 - Planning
Classifier: License :: OSI Approved :: Apache Software License
Classifier: Programming Language :: Python
Classifier: Intended Audience :: Developers
